testudos/__init__.py
testudos/cli.py
testudos/config.py
testudos/coverage.py
testudos/executor.py
testudos/multi_runner.py
testudos/python_version.py
testudos/runner.py
testudos/ui.py
testudos/versions.py
testudos/workspace.py
testudos-0.14.0.dist-info/METADATA
testudos-0.14.0.dist-info/WHEEL
testudos-0.14.0.dist-info/entry_points.txt
testudos-0.14.0.dist-info/licenses/LICENSE
testudos-0.14.0.dist-info/RECORD
