Metadata-Version: 2.4
Name: testudos
Version: 0.14.0
Summary: A testing harness for Python packages using uv's isolated environments
Project-URL: Homepage, https://github.com/martinristovski/testudos
Project-URL: Documentation, https://github.com/martinristovski/testudos/blob/main/README.md
Project-URL: Repository, https://github.com/martinristovski/testudos
Project-URL: Issues, https://github.com/martinristovski/testudos/issues
Author: Martin Ristovski
License: MIT
License-File: LICENSE
Keywords: multi-version,python,testing,uv
Classifier: Development Status :: 3 - Alpha
Classifier: Intended Audience :: Developers
Classifier: License :: OSI Approved :: MIT License
Classifier: Programming Language :: Python :: 3
Classifier: Programming Language :: Python :: 3.10
Classifier: Programming Language :: Python :: 3.11
Classifier: Programming Language :: Python :: 3.12
Classifier: Programming Language :: Python :: 3.13
Classifier: Topic :: Software Development :: Testing
Requires-Python: >=3.10
Requires-Dist: coverage>=7.13.0
Requires-Dist: httpx>=0.28.0
Requires-Dist: packaging>=25.0
Requires-Dist: pytest-asyncio>=1.3.0
Requires-Dist: pytest-cov>=7.0.0
Requires-Dist: pytest>=9.0.0
Requires-Dist: rich>=14.0.0
Requires-Dist: tomli>=2.0.0; python_version < '3.11'
Requires-Dist: typer>=0.21.0
Provides-Extra: dev
Requires-Dist: mypy>=1.19.0; extra == 'dev'
Requires-Dist: ruff>=0.14.0; extra == 'dev'
